{
  "username": "watchingmarkets",
  "tweets_count": 60,
  "tweets": [
    {
      "parse_timestamp": "2025-09-03T20:57:07.120401+00:00",
      "text": "$PUMP goes for the second TP target at 0.0041$",
      "timestamp": "2025-09-03T17:12:23.000Z",
      "url": "https://x.comhttps://x.com/watchingmarkets/status/1963288977894412738",
      "replies": 2,
      "reposts": 1,
      "likes": 23,
      "views": 2061
    },
    {
      "parse_timestamp": "2025-09-03T20:57:07.138456+00:00",
      "text": "Peace comes when you let go of the urge to rush wealth and step back from the noise of daily life. \n\nGiving yourself a few hours to train, be with your partner, read, or work on an idea without distraction is where balance is found. \n\nDon’t forget to live along the way. \n\nSee you",
      "timestamp": "2025-09-03T15:32:36.000Z",
      "url": "https://x.comhttps://x.com/watchingmarkets/status/1963263866718355649",
      "replies": 9,
      "reposts": 5,
      "likes": 110,
      "views": 3794
    },
    {
      "parse_timestamp": "2025-09-03T20:57:07.155839+00:00",
      "text": "Higher.",
      "timestamp": "2025-09-03T14:43:26.000Z",
      "url": "https://x.comhttps://x.com/watchingmarkets/status/1963251495878418763",
      "replies": 22,
      "reposts": 2,
      "likes": 155,
      "views": 5092
    },
    {
      "parse_timestamp": "2025-09-03T20:57:07.206910+00:00",
      "text": "LTF BO\n\nNext HTF BO attempt soon. \n\n#TOTAL2",
      "timestamp": "2025-09-03T14:39:23.000Z",
      "url": "https://x.comhttps://x.com/watchingmarkets/status/1963250475928612907",
      "replies": 2,
      "reposts": 1,
      "likes": 25,
      "views": 2383
    },
    {
      "parse_timestamp": "2025-09-03T20:57:07.192157+00:00",
      "text": "",
      "timestamp": "2025-09-03T14:35:04.000Z",
      "url": "https://x.comhttps://x.com/watchingmarkets/status/1963249390753132946",
      "replies": 5,
      "reposts": 0,
      "likes": 21,
      "views": 2679
    },
    {
      "parse_timestamp": "2025-09-03T20:57:11.068345+00:00",
      "text": "Solana cycle",
      "timestamp": "2025-09-03T14:05:41.000Z",
      "url": "https://x.comhttps://x.com/watchingmarkets/status/1963241994819420337",
      "replies": 29,
      "reposts": 6,
      "likes": 187,
      "views": 8677
    },
    {
      "parse_timestamp": "2025-09-03T20:57:07.177223+00:00",
      "text": "I know the temptation to trade this with leverage is huge, especially when the setup looks as clean as this falling wedge, pointing to a breakout and a bullish month. But I avoid getting greedy and just hold my spot bags from the lows. I set my TP targets in advance, and on",
      "timestamp": "2025-09-03T10:37:21.000Z",
      "url": "https://x.comhttps://x.com/watchingmarkets/status/1963189567420559718",
      "replies": 2,
      "reposts": 0,
      "likes": 36,
      "views": 6522
    },
    {
      "parse_timestamp": "2025-09-03T20:57:11.115550+00:00",
      "text": "While majority of CT is busy debating whether the ‘top is in,’ we’re already 40%+ up on our $PUMP trade, outperforming everyone.",
      "timestamp": "2025-09-03T10:28:04.000Z",
      "url": "https://x.comhttps://x.com/watchingmarkets/status/1963187230517641401",
      "replies": 9,
      "reposts": 1,
      "likes": 32,
      "views": 3338
    },
    {
      "parse_timestamp": "2025-09-03T20:57:11.098397+00:00",
      "text": "Now the spotlight belongs to the bulls.\n\nFull bull.",
      "timestamp": "2025-09-03T10:24:58.000Z",
      "url": "https://x.comhttps://x.com/watchingmarkets/status/1963186448670372007",
      "replies": 9,
      "reposts": 1,
      "likes": 53,
      "views": 3616
    },
    {
      "parse_timestamp": "2025-09-03T20:57:11.156347+00:00",
      "text": "In my entire trading journey, I’ve never felt this confident in my positions, driven by a clean setup and a textbook high-timeframe cup-and-handle. \n\nWhile the TL unravels in crashes, overtrading, and emotional noise, I remain steady. \n\nLet them chase the drama, I’m locked in on",
      "timestamp": "2025-09-03T06:46:40.000Z",
      "url": "https://x.comhttps://x.com/watchingmarkets/status/1963131510900355499",
      "replies": 9,
      "reposts": 1,
      "likes": 64,
      "views": 3830
    },
    {
      "parse_timestamp": "2025-09-03T20:57:11.131173+00:00",
      "text": "$BTC -> $ETH -> $SOL -> #OTHERS",
      "timestamp": "2025-09-03T06:43:09.000Z",
      "url": "https://x.comhttps://x.com/watchingmarkets/status/1963130625671516399",
      "replies": 2,
      "reposts": 3,
      "likes": 41,
      "views": 4129
    },
    {
      "parse_timestamp": "2025-09-03T20:57:11.083807+00:00",
      "text": "Gm \n\nI’m impressed by the relative strength in $SOL and $PUMP\n\nBut don’t overlook $ETH \n\nIt’s forming a clean falling wedge pattern, and September is shaping up to be bullish.\n\nPatience.",
      "timestamp": "2025-09-03T06:38:03.000Z",
      "url": "https://x.comhttps://x.com/watchingmarkets/status/1963129344718409896",
      "replies": 24,
      "reposts": 5,
      "likes": 115,
      "views": 11287
    },
    {
      "parse_timestamp": "2025-09-03T20:57:07.096894+00:00",
      "text": "$PUMP it.\n\nStill max ROI.",
      "timestamp": "2025-09-02T14:21:38.000Z",
      "url": "https://x.comhttps://x.com/watchingmarkets/status/1962883619329863937",
      "replies": 10,
      "reposts": 2,
      "likes": 24,
      "views": 4391
    },
    {
      "parse_timestamp": "2025-09-03T20:57:11.232166+00:00",
      "text": "",
      "timestamp": "2025-09-02T13:52:55.000Z",
      "url": "https://x.comhttps://x.com/watchingmarkets/status/1962876394880266395",
      "replies": 7,
      "reposts": 2,
      "likes": 50,
      "views": 3321
    },
    {
      "parse_timestamp": "2025-09-03T20:57:11.176779+00:00",
      "text": "Chop, chop, chop, until PA breaks to the upside. Not a question of if, but when (this week). I’m patient.\n\n#TOTAL2",
      "timestamp": "2025-09-02T12:55:53.000Z",
      "url": "https://x.comhttps://x.com/watchingmarkets/status/1962862042517209531",
      "replies": 7,
      "reposts": 2,
      "likes": 50,
      "views": 4524
    },
    {
      "parse_timestamp": "2025-09-03T20:57:13.374491+00:00",
      "text": "There will always be opportunities to make profits for the rest of your life. \n\nDon’t give in to the pressure of trying to do everything hastily or all at once. You have plenty of time. \n\nStep back, zoom out, and study the higher timeframes. Build your setup around those HTFs,",
      "timestamp": "2025-09-02T12:31:52.000Z",
      "url": "https://x.comhttps://x.com/watchingmarkets/status/1962855997698896278",
      "replies": 2,
      "reposts": 4,
      "likes": 50,
      "views": 5511
    },
    {
      "parse_timestamp": "2025-09-03T20:57:13.359987+00:00",
      "text": "If you’re truly disciplined, you can take your quality of life to the next level by doing one simple thing: \n\nPrioritize sleep over late-night screen time. \n\nThe impact on your entire day is enormous.",
      "timestamp": "2025-09-02T11:10:42.000Z",
      "url": "https://x.comhttps://x.com/watchingmarkets/status/1962835569643335814",
      "replies": 6,
      "reposts": 2,
      "likes": 80,
      "views": 4939
    },
    {
      "parse_timestamp": "2025-09-03T20:56:24.877489+00:00",
      "text": "I bought more $PENDLE\n\nI expect it to follow $ENA, break out of this downtrend, and move into price discovery.",
      "timestamp": "2025-09-02T11:01:34.000Z",
      "url": "https://x.comhttps://x.com/watchingmarkets/status/1962833271525359814",
      "replies": 3,
      "reposts": 2,
      "likes": 19,
      "views": 5074
    },
    {
      "parse_timestamp": "2025-09-03T20:57:13.407585+00:00",
      "text": "Staying true to your principles will always outweigh chasing more money. In the end, you have to live a long life with your own conscience, and clear values built on honesty and self-respect are worth far more than any money earned the wrong way.",
      "timestamp": "2025-09-02T10:12:37.000Z",
      "url": "https://x.comhttps://x.com/watchingmarkets/status/1962820955438190942",
      "replies": 5,
      "reposts": 8,
      "likes": 129,
      "views": 6193
    },
    {
      "parse_timestamp": "2025-09-03T20:57:13.438000+00:00",
      "text": "If you’re in a phase of life where family issues weigh on you, money is tight, your job doesn’t feel right, and you’re trying to make trading work on the side, but you’re overtrading, emotional, and feeling the pressure of financial stress, let me tell you this:\n\nIf you can",
      "timestamp": "2025-09-02T09:17:20.000Z",
      "url": "https://x.comhttps://x.com/watchingmarkets/status/1962807041585451276",
      "replies": 7,
      "reposts": 20,
      "likes": 136,
      "views": 5191
    },
    {
      "parse_timestamp": "2025-09-03T20:57:13.421855+00:00",
      "text": "Timing beats time.\n\nCash is king.\n\nTrade the setup.\n\nNo fear. No greed.\n\nCut losses without emotion.\n\nPrioritize relative strength.\n\nCatch narratives early.\n\nThink sharper than your timeline.",
      "timestamp": "2025-09-02T09:10:15.000Z",
      "url": "https://x.comhttps://x.com/watchingmarkets/status/1962805258926584190",
      "replies": 4,
      "reposts": 6,
      "likes": 116,
      "views": 4737
    },
    {
      "parse_timestamp": "2025-09-03T20:57:13.344955+00:00",
      "text": "Let me say this to anyone aiming for 100k or 1m:\n\nIf you don’t respect 5k–10k profits, because you’re desperately trying to squeeze out more than your planned take-profits, constantly moving targets higher out of pure greed, you will fail in the long run.\n\nSetups must be planned",
      "timestamp": "2025-09-02T09:01:01.000Z",
      "url": "https://x.comhttps://x.com/watchingmarkets/status/1962802936158757343",
      "replies": 56,
      "reposts": 78,
      "likes": 730,
      "views": 43435
    },
    {
      "parse_timestamp": "2025-09-03T20:57:13.468682+00:00",
      "text": "Don’t forget to take solid profits in Q4 2025 - Q2 2026. \n\nThe playbook is there, set, and more obvious than ever. Use it. \n\nBreakout pump, retest, final big leg up, that would be the ideal case. But even selling into the breakout pump already gives a good feeling. So set",
      "timestamp": "2025-09-02T08:52:15.000Z",
      "url": "https://x.comhttps://x.com/watchingmarkets/status/1962800729103483084",
      "replies": 4,
      "reposts": 0,
      "likes": 41,
      "views": 4432
    },
    {
      "parse_timestamp": "2025-09-03T20:57:13.453978+00:00",
      "text": "$ENA has been another clean max-ROI setup since 0.28$\n\nMost early buyers have likely been shaken out by now, setting the stage for higher levels soon.",
      "timestamp": "2025-09-02T08:38:33.000Z",
      "url": "https://x.comhttps://x.com/watchingmarkets/status/1962797282685866074",
      "replies": 3,
      "reposts": 0,
      "likes": 26,
      "views": 3489
    },
    {
      "parse_timestamp": "2025-09-03T20:56:24.828753+00:00",
      "text": "Gm \n\nI hope you managed to sit through and weather the three days of choppy PA just as I did. \n\nAs expected, we saw some green PA during the night from Monday to Tuesday, which now has the potential to kick off bullish momentum for the first two weeks of September. \n\nThe charts",
      "timestamp": "2025-09-02T08:26:28.000Z",
      "url": "https://x.comhttps://x.com/watchingmarkets/status/1962794240934613016",
      "replies": 33,
      "reposts": 8,
      "likes": 184,
      "views": 14310
    },
    {
      "parse_timestamp": "2025-09-03T20:57:16.035011+00:00",
      "text": "Institutions/TradFi: “We’re about to max bid Ethereum and Solana.”\n\nSome crypto OGs: “Top’s in, time to flip bearish right here.”\n\nI’m really curious to see how the playbook plays out in the end. Genuinely curious.",
      "timestamp": "2025-09-01T08:15:46.000Z",
      "url": "https://x.comhttps://x.com/watchingmarkets/status/1962429158887133367",
      "replies": 3,
      "reposts": 3,
      "likes": 51,
      "views": 4433
    },
    {
      "parse_timestamp": "2025-09-03T20:57:13.497726+00:00",
      "text": "Breakout on the LTF setup here sets up another HTF BO attempt. \n\nA massive ascending triangle is in play, a breakout would send #TOTAL2 into price discovery toward 2T.",
      "timestamp": "2025-09-01T08:12:08.000Z",
      "url": "https://x.comhttps://x.com/watchingmarkets/status/1962428246244348070",
      "replies": 3,
      "reposts": 3,
      "likes": 36,
      "views": 4917
    },
    {
      "parse_timestamp": "2025-09-03T20:57:16.049384+00:00",
      "text": "Top performer, pure relative strength.\n\n$PUMP it.",
      "timestamp": "2025-09-01T07:44:12.000Z",
      "url": "https://x.comhttps://x.com/watchingmarkets/status/1962421213948440733",
      "replies": 5,
      "reposts": 1,
      "likes": 26,
      "views": 4342
    },
    {
      "parse_timestamp": "2025-09-03T20:57:21.073740+00:00",
      "text": "September will be bullish.",
      "timestamp": "2025-09-01T07:29:48.000Z",
      "url": "https://x.comhttps://x.com/watchingmarkets/status/1962417592859042160",
      "replies": 39,
      "reposts": 29,
      "likes": 314,
      "views": 10726
    },
    {
      "parse_timestamp": "2025-09-03T20:57:21.087780+00:00",
      "text": "Outlook for Altcoins in September 2025\n\n#TOTAL2 (1D)",
      "timestamp": "2025-09-01T07:00:59.000Z",
      "url": "https://x.comhttps://x.com/watchingmarkets/status/1962410341901447469",
      "replies": 4,
      "reposts": 2,
      "likes": 67,
      "views": 5170
    },
    {
      "parse_timestamp": "2025-09-03T20:57:21.115579+00:00",
      "text": "On-chain looks brutal, volatility feels like a 30% SOL crash. Total Wild West. Got singed chasing some meme coin entries.",
      "timestamp": "2025-09-01T06:27:42.000Z",
      "url": "https://x.comhttps://x.com/watchingmarkets/status/1962401963556942226",
      "replies": 14,
      "reposts": 1,
      "likes": 22,
      "views": 3759
    },
    {
      "parse_timestamp": "2025-09-03T20:57:21.101495+00:00",
      "text": "Even $BTC looks good here, at the bottom of the falling wedge (4h) and within a strong support zone. \n\nIt’s unlikely that we break below.",
      "timestamp": "2025-09-01T06:17:48.000Z",
      "url": "https://x.comhttps://x.com/watchingmarkets/status/1962399472261963804",
      "replies": 4,
      "reposts": 2,
      "likes": 42,
      "views": 3598
    },
    {
      "parse_timestamp": "2025-09-03T20:57:13.483081+00:00",
      "text": "Gm \n\nFinal day to stay patient, I expect today will set September’s lows. \n\nWishing everyone a profitable month ahead, let’s make it one of breakouts and true price discovery.",
      "timestamp": "2025-09-01T04:35:56.000Z",
      "url": "https://x.comhttps://x.com/watchingmarkets/status/1962373834889114079",
      "replies": 32,
      "reposts": 11,
      "likes": 255,
      "views": 16092
    },
    {
      "parse_timestamp": "2025-09-03T20:57:21.129664+00:00",
      "text": "Gm",
      "timestamp": "2025-08-31T07:53:02.000Z",
      "url": "https://x.comhttps://x.com/watchingmarkets/status/1962061051165389123",
      "replies": 75,
      "reposts": 1,
      "likes": 198,
      "views": 8661
    },
    {
      "parse_timestamp": "2025-09-03T20:57:24.880622+00:00",
      "text": "1. Just knocked out a 10K run, 100 burpees, 100 squats, 100 sit-ups.\n\nPost-workout hype at its peak.\n\n2. Tonight I’ll read a few more pages of „Think and Grow Rich“ by Napoleon Hill.\n\n3. Checked the market structure on the TOTAL2, looked solid, trend holds.\n\nLet my first TP",
      "timestamp": "2025-08-30T11:02:27.000Z",
      "url": "https://x.comhttps://x.com/watchingmarkets/status/1961746330436427791",
      "replies": 15,
      "reposts": 0,
      "likes": 95,
      "views": 4814
    },
    {
      "parse_timestamp": "2025-09-03T20:57:21.162849+00:00",
      "text": "Do it every single day.",
      "timestamp": "2025-08-30T10:54:11.000Z",
      "url": "https://x.comhttps://x.com/watchingmarkets/status/1961744250623721556",
      "replies": 6,
      "reposts": 0,
      "likes": 62,
      "views": 5205
    },
    {
      "parse_timestamp": "2025-09-03T20:57:21.149198+00:00",
      "text": "The key to fitness is consistency.\n\nThe key to education is consistency.\n\nThe key to trading profitably is consistency.\n\nEverything comes back to one rule:\n\nBe consistent.",
      "timestamp": "2025-08-30T10:46:01.000Z",
      "url": "https://x.comhttps://x.com/watchingmarkets/status/1961742195297309018",
      "replies": 21,
      "reposts": 23,
      "likes": 200,
      "views": 9949
    },
    {
      "parse_timestamp": "2025-09-03T20:57:24.925851+00:00",
      "text": "Doing nothing until Tuesday.",
      "timestamp": "2025-08-30T09:18:55.000Z",
      "url": "https://x.comhttps://x.com/watchingmarkets/status/1961720275008925732",
      "replies": 7,
      "reposts": 2,
      "likes": 66,
      "views": 3825
    },
    {
      "parse_timestamp": "2025-09-03T20:57:24.940092+00:00",
      "text": "The uncomfortable truth for new on-chain traders:\n\nYes, I reached financial freedom, mainly through on-chain trading.\n\nBut before that, I spent over 7 years unprofitable: failing again and again, conviction shattered, mindset broken, facing the choice to quit hundreds of times.",
      "timestamp": "2025-08-30T09:08:09.000Z",
      "url": "https://x.comhttps://x.com/watchingmarkets/status/1961717568697237680",
      "replies": 19,
      "reposts": 15,
      "likes": 219,
      "views": 9899
    },
    {
      "parse_timestamp": "2025-09-03T20:57:24.909838+00:00",
      "text": "Port’s trading around ATH, not sure what TL is crashing out about.\n\nFocus on relative strength. Don’t overtrade your positions. Daytrade memes. Set TP targets, stack limit orders. Otherwise: do nothing.",
      "timestamp": "2025-08-30T08:44:13.000Z",
      "url": "https://x.comhttps://x.com/watchingmarkets/status/1961711542266646782",
      "replies": 10,
      "reposts": 0,
      "likes": 42,
      "views": 4764
    },
    {
      "parse_timestamp": "2025-09-03T20:57:24.982353+00:00",
      "text": "Pretty accurate.",
      "timestamp": "2025-08-30T08:12:06.000Z",
      "url": "https://x.comhttps://x.com/watchingmarkets/status/1961703462753701996",
      "replies": 0,
      "reposts": 0,
      "likes": 0,
      "views": 2947
    },
    {
      "parse_timestamp": "2025-09-03T20:57:24.894902+00:00",
      "text": "Gm \n\nMy portfolio is fully concentrated on the Solana ecosystem and Ethereum DeFi.\n\nSolana cycle $SOL $PUMP $JUP \n\nDeFi $LINK $ENA $AAVE $PENDLE \n\nMy Layer 1 bet from here: $SEI \n\nMy Layer 2 bet from here: $ARB\n\nMemes: $BONK $PENGU $Uranus\n\nBearish on: $BTC.D and bear market",
      "timestamp": "2025-08-30T07:55:46.000Z",
      "url": "https://x.comhttps://x.com/watchingmarkets/status/1961699349039026432",
      "replies": 42,
      "reposts": 12,
      "likes": 208,
      "views": 14160
    },
    {
      "parse_timestamp": "2025-09-03T20:57:25.010487+00:00",
      "text": "Since entry, $PUMP is the strongest performer in the past 24 hours and ranks as the third-highest gainer over the last 7 days across the entire crypto market.   \n\nCould this be shaping up for a max ROI run like PENGU?",
      "timestamp": "2025-08-30T07:23:40.000Z",
      "url": "https://x.comhttps://x.com/watchingmarkets/status/1961691274462851316",
      "replies": 11,
      "reposts": 1,
      "likes": 30,
      "views": 3680
    },
    {
      "parse_timestamp": "2025-09-03T20:57:24.996440+00:00",
      "text": "First TP + 33%\n\n$PUMP",
      "timestamp": "2025-08-30T07:08:08.000Z",
      "url": "https://x.comhttps://x.com/watchingmarkets/status/1961687362276061267",
      "replies": 6,
      "reposts": 0,
      "likes": 39,
      "views": 3888
    },
    {
      "parse_timestamp": "2025-09-03T20:57:27.140279+00:00",
      "text": "Falling wedge breakout.\n\nAnother bottomed inverse H&S setting up.\n\nLast time we saw this, the chart was 1:1 the PENGU playbook.\n\nBreak the neckline and $BONK it.\n\nTP levels stacked up to +100%",
      "timestamp": "2025-08-29T22:39:16.000Z",
      "url": "https://x.comhttps://x.com/watchingmarkets/status/1961559303669583916",
      "replies": 2,
      "reposts": 0,
      "likes": 15,
      "views": 2758
    },
    {
      "parse_timestamp": "2025-09-03T20:57:27.182871+00:00",
      "text": "#TOTAL3",
      "timestamp": "2025-08-29T22:22:32.000Z",
      "url": "https://x.comhttps://x.com/watchingmarkets/status/1961555090529047008",
      "replies": 7,
      "reposts": 2,
      "likes": 44,
      "views": 2876
    },
    {
      "parse_timestamp": "2025-09-03T20:57:27.169145+00:00",
      "text": "#OTHERS not even reall started\n\nMeme coins on Solana were/are this cycles DeFi/NFT parabola.\n\nBitcoin pumped from 16k to 124k\n\nHeavy rotation into ETH, pumped from 1.5k to 4.8k (price discovery soon)\n\nBitcoin dominance broke down (last time in 2021 - altcoin szn)\n\nNow: bullish",
      "timestamp": "2025-08-29T22:11:55.000Z",
      "url": "https://x.comhttps://x.com/watchingmarkets/status/1961552421190046002",
      "replies": 3,
      "reposts": 7,
      "likes": 37,
      "views": 3718
    },
    {
      "parse_timestamp": "2025-09-03T20:57:27.155817+00:00",
      "text": "This weekend is about waiting for the new month to begin and simply leaving the weekend’s PA behind, with focus on the entire Solana ecosystem. Monday to Tuesday night will be important again. \n\nGn\n\n$SOL $PUMP $JUP $BONK",
      "timestamp": "2025-08-29T21:12:11.000Z",
      "url": "https://x.comhttps://x.com/watchingmarkets/status/1961537386011398290",
      "replies": 14,
      "reposts": 1,
      "likes": 131,
      "views": 8708
    },
    {
      "parse_timestamp": "2025-09-03T20:57:27.221088+00:00",
      "text": "$PUMP it.",
      "timestamp": "2025-08-29T16:35:12.000Z",
      "url": "https://x.comhttps://x.com/watchingmarkets/status/1961467682269614449",
      "replies": 3,
      "reposts": 1,
      "likes": 29,
      "views": 3411
    },
    {
      "parse_timestamp": "2025-09-03T20:57:29.388227+00:00",
      "text": "$SOL $JUP $PUMP",
      "timestamp": "2025-08-29T12:35:27.000Z",
      "url": "https://x.comhttps://x.com/watchingmarkets/status/1961407346510344597",
      "replies": 4,
      "reposts": 0,
      "likes": 31,
      "views": 3185
    },
    {
      "parse_timestamp": "2025-09-03T20:57:29.373567+00:00",
      "text": "The whole $PUMP setup is perfect, everything lines up, and the current sheer strength only reinforces the thesis.",
      "timestamp": "2025-08-29T12:21:23.000Z",
      "url": "https://x.comhttps://x.com/watchingmarkets/status/1961403807155228765",
      "replies": 8,
      "reposts": 2,
      "likes": 36,
      "views": 4246
    },
    {
      "parse_timestamp": "2025-09-03T20:57:29.402138+00:00",
      "text": "CT culture is so entertaining and sharp that leaving this space feels impossible. It’s one never-ending show of inside jokes only this niche can truly get and enjoy. Best of all, the interaction itself is fun. CT has built such a distinct culture that you’re always left with fomo",
      "timestamp": "2025-08-29T11:18:30.000Z",
      "url": "https://x.comhttps://x.com/watchingmarkets/status/1961387983476551932",
      "replies": 15,
      "reposts": 2,
      "likes": 103,
      "views": 6417
    },
    {
      "parse_timestamp": "2025-09-03T20:57:24.969109+00:00",
      "text": "Higher for altcoins.\n\n$BTC.D",
      "timestamp": "2025-08-29T10:43:50.000Z",
      "url": "https://x.comhttps://x.com/watchingmarkets/status/1961379259160654225",
      "replies": 13,
      "reposts": 1,
      "likes": 63,
      "views": 5906
    },
    {
      "parse_timestamp": "2025-09-03T20:57:24.954391+00:00",
      "text": "The final weekend of August is shaping up to be a classic end-of-month shakeout, and it will set the tone for how we enter September.\n\nWe’ve seen plenty of end-of-month weekend shakeouts before, and how often have we bounced back by the 2nd, kicking off new bullish momentum and",
      "timestamp": "2025-08-29T09:04:20.000Z",
      "url": "https://x.comhttps://x.com/watchingmarkets/status/1961354219631337705",
      "replies": 22,
      "reposts": 11,
      "likes": 150,
      "views": 12824
    },
    {
      "parse_timestamp": "2025-09-03T20:57:27.208558+00:00",
      "text": "Showing more strength than the rest of the market.\n\n$PUMP (1h)",
      "timestamp": "2025-08-29T08:36:53.000Z",
      "url": "https://x.comhttps://x.com/watchingmarkets/status/1961347311264543101",
      "replies": 2,
      "reposts": 2,
      "likes": 22,
      "views": 5112
    },
    {
      "parse_timestamp": "2025-09-03T20:57:27.195574+00:00",
      "text": "Gm \n\nFocus on relative strength: $SOL $PUMP $JUP",
      "timestamp": "2025-08-29T07:24:33.000Z",
      "url": "https://x.comhttps://x.com/watchingmarkets/status/1961329108140413238",
      "replies": 36,
      "reposts": 3,
      "likes": 86,
      "views": 8693
    },
    {
      "parse_timestamp": "2025-09-03T20:57:27.126695+00:00",
      "text": "Bonk guy will be right.\n\n$BONK (1D) \n@bonk_inu",
      "timestamp": "2025-08-28T10:04:12.000Z",
      "url": "https://x.comhttps://x.com/watchingmarkets/status/1961006897504333896",
      "replies": 40,
      "reposts": 20,
      "likes": 210,
      "views": 33940
    },
    {
      "parse_timestamp": "2025-09-03T20:57:07.080844+00:00",
      "text": "$PUMP (1D) \n@pumpdotfun\n \n\nEntry: 0.0027$\n\nSL: 0.00249$\n\nTP: 0.0036/0.0041/0.0046/0.0067",
      "timestamp": "2025-08-25T06:59:44.000Z",
      "url": "https://x.comhttps://x.com/watchingmarkets/status/1959873311317627352",
      "replies": 18,
      "reposts": 4,
      "likes": 156,
      "views": 29801
    },
    {
      "parse_timestamp": "2025-09-03T20:57:27.235528+00:00",
      "text": "The thesis is obvious, and the TA looks clean. The real question is whether the internet-capital-markets narrative of believe will prevail, and what’s actually being built behind the scenes. To me, there are two extremes: those who call it all a scam, a failed project with a dev",
      "timestamp": "2025-08-25T06:52:32.000Z",
      "url": "https://x.comhttps://x.com/watchingmarkets/status/1959871498501402726",
      "replies": 9,
      "reposts": 2,
      "likes": 73,
      "views": 12715
    },
    {
      "parse_timestamp": "2025-09-03T20:56:24.793103+00:00",
      "text": "I am currently trading on https://axiom.trade/@mwatcher\n\nYou can actually do everything here, direct registration with an e-mail and you have your wallet.\n\nI started trading there because I think that farming points could lead to an airdrop of an Axiom token at some point.\n\nSo far, I",
      "timestamp": "2025-03-26T10:54:30.000Z",
      "url": "https://x.comhttps://x.com/watchingmarkets/status/1904849436054085795",
      "replies": 50,
      "reposts": 18,
      "likes": 285,
      "views": 386288
    }
  ]
}